svv_accel/__init__.py
svv_accel/domain/routines/c_allocate.cp312-win32.pyd
svv_accel/domain/routines/c_sample.cp312-win32.pyd
svv_accel/simulation/utils/close_segments.cp312-win32.pyd
svv_accel/simulation/utils/extract.cp312-win32.pyd
svv_accel/tree/utils/c_angle.cp312-win32.pyd
svv_accel/tree/utils/c_basis.cp312-win32.pyd
svv_accel/tree/utils/c_close.cp312-win32.pyd
svv_accel/tree/utils/c_extend.cp312-win32.pyd
svv_accel/tree/utils/c_local_optimize.cp312-win32.pyd
svv_accel/tree/utils/c_obb.cp312-win32.pyd
svv_accel/tree/utils/c_update.cp312-win32.pyd
svv_accel/utils/spatial/c_distance.cp312-win32.pyd
svv_accelerated-0.0.43.dist-info/METADATA
svv_accelerated-0.0.43.dist-info/WHEEL
svv_accelerated-0.0.43.dist-info/top_level.txt
svv_accelerated-0.0.43.dist-info/RECORD
