Metadata-Version: 2.4
Name: svv-accelerated
Version: 0.0.43
Summary: svVascularize (svv): A synthetic vascular generation, modeling, and simulation package
Author: Zachary Sexton
Author-email: zsexton@stanford.edu
License: MIT
Keywords: modeling,simulation,tissue-engineering,3d-printing,fluid-dynamics
Classifier: Intended Audience :: Science/Research
Classifier: License :: OSI Approved :: MIT License
Classifier: Programming Language :: Python :: 3.9
Classifier: Programming Language :: Python :: 3.10
Classifier: Programming Language :: Python :: 3.11
Classifier: Programming Language :: Python :: 3.12
Classifier: Topic :: Scientific/Engineering
Classifier: Operating System :: Microsoft :: Windows
Classifier: Operating System :: POSIX :: Linux
Classifier: Operating System :: POSIX
Classifier: Operating System :: Unix
Classifier: Operating System :: MacOS
Requires-Python: >=3.9
Requires-Dist: numpy>=1.24; python_version < "3.12"
Requires-Dist: numpy>=1.26; python_version >= "3.12"
Requires-Dist: scipy>=1.10.1; python_version < "3.12"
Requires-Dist: scipy>=1.12.0; python_version >= "3.12"
Requires-Dist: matplotlib>=3.7.5; python_version < "3.12"
Requires-Dist: matplotlib>=3.8; python_version >= "3.12"
Requires-Dist: Cython~=3.0.7
Requires-Dist: usearch
Requires-Dist: scikit-image
Requires-Dist: tetgen
Requires-Dist: trimesh[all]
Requires-Dist: meshio
Requires-Dist: open3d
Requires-Dist: pyvista>=0.44.2
Requires-Dist: scikit-learn
Requires-Dist: tqdm
Requires-Dist: pymeshfix==0.17.0
Requires-Dist: numexpr
Requires-Dist: pyvistaqt>=0.11.0
Requires-Dist: pyside6>=6.4.0
Dynamic: author
Dynamic: author-email
Dynamic: classifier
Dynamic: description
Dynamic: description-content-type
Dynamic: keywords
Dynamic: license
Dynamic: requires-dist
Dynamic: requires-python
Dynamic: summary
